jam_tree/__init__.py
jam_tree/ai_analyzer.py
jam_tree/cli.py
jam_tree/config.py
jam_tree/directory_scanner.py
jam_tree/output_generator.py
jam_tree/project_bootstrap.py
jam_tree-0.1.7.dist-info/LICENSE
jam_tree-0.1.7.dist-info/METADATA
jam_tree-0.1.7.dist-info/WHEEL
jam_tree-0.1.7.dist-info/entry_points.txt
jam_tree-0.1.7.dist-info/top_level.txt
jam_tree-0.1.7.dist-info/RECORD
