Metadata-Version: 2.1
Name: jam-tree
Version: 0.1.7
Summary: Ferramenta para gerar árvore de diretórios com análise de IA
Home-page: https://github.com/GitHubJordan/JAM-Tree
Author: Jordan Adelino
Author-email: jordanadelino.info@gmail.com
License: UNKNOWN
Project-URL: Documentation, https://jam-tree.readthedocs.io/
Project-URL: Bug Reports, https://github.com/GitHubJordan/JAM-Tree/issues
Project-URL: Funding, https://airtm.me/jordan_adelino
Project-URL: Say Thanks!, https://jordanadelino.info
Project-URL: Source, https://github.com/GitHubJordan/JAM-Tree/
Keywords: jam-tree,setuptools,development,ai,analyzer,tree,directory,framework
Platform: UNKNOWN
Classifier: Development Status :: 5 - Production/Stable
Classifier: Environment :: Console
Classifier: Natural Language :: Portuguese (Brazilian)
Classifier: Intended Audience :: End Users/Desktop
Classifier: Intended Audience :: Developers
Classifier: Topic :: Software Development :: Build Tools
Classifier: Programming Language :: Python :: 3.8
Classifier: Programming Language :: Python :: 3.9
Classifier: Programming Language :: Python :: 3.10
Classifier: License :: OSI Approved :: MIT License
License-File: LICENSE
Requires-Dist: click>=8.1.8
Requires-Dist: google-genai>=1.3.0
Requires-Dist: rich>=13.9.4
